pushikoo_interface/__init__.py
pushikoo_interface/adapter.py
pushikoo_interface/structure.py
pushikoo_interface/tester.py
pushikoo_interface/util.py
pushikoo_interface-0.3.1.dist-info/licenses/LICENSE
pushikoo_interface-0.3.1.dist-info/METADATA
pushikoo_interface-0.3.1.dist-info/WHEEL
pushikoo_interface-0.3.1.dist-info/top_level.txt
pushikoo_interface-0.3.1.dist-info/RECORD
