Metadata-Version: 2.4
Name: pushikoo-interface
Version: 0.3.1
Summary: Adapter interface definitions for Pushikoo
Author: Pushikoo
Project-URL: Homepage, https://github.com/Pushikoo/pushikoo-interface
Classifier: Programming Language :: Python :: 3
Classifier: Operating System :: OS Independent
Requires-Python: >=3.10
License-File: LICENSE
Requires-Dist: pydantic
Provides-Extra: dev
Requires-Dist: ruff; extra == "dev"
Requires-Dist: pytest; extra == "dev"
Dynamic: license-file
